Workbook
Name ACTION: #REF!
Name ACTION: #REF!

Sheet Cover
B2: TEST REPORT DOCUMENT
A4: Project Name | B4: SmartDroneInspection | E4: *Enter team/member name*
A5: Project Code | B5: SEP490 — *confirm with project owner* | E5: Issue Date | F5: 2026-10-09
A6: Document Code | B6: =B5&"_"&"XXX"&"_"&"vx.x" | E6: Version | F6: 3.5 (Scope baselines rewritten from Report 3 itself: every FE file now carries its Report 3 title and reproduces the real MF1-01…MF1-14, MF2-01…MF2-12, MF4 responsibility table and §3.9 role rules instead of marketplace-era summaries. Reconciled against the supplied workbook by reading it directly — corrected the cover change-table headers, corrected `Module code` to carry the feature-sheet name rather than the sheet name, and documented four template defects including a stray `6` in `Feature 2!A18` that `COUNTA` would count as a sixth case. No case ID, status, round, date, tester or total changed — still 5 cases, all `Passed`.)
A9: Record of change
A10: Effective Date | B10: Version | C10: Change Item | D10: *A,D,M | E10: Change description | F10: Reference
A11: 2026-09-22 | B11: 0.1 | C11: Report 5 working source | D11: A | E11: Created the editable test-case structure from the supplied workbook without changing the original template layout. | F11: `template/Report5_Test Report.xlsx`
A12: 2026-09-22 | B12: 0.2 | C12: FE ownership alignment | D12: M | E12: Added FE-01 through FE-07 mapping, recorded the FE-01 W3 auth/migration gate, and split WF3 traceability across FE-04, FE-05, and FE-06 without changing test IDs or workbook sheets. | F12: Jira SCRUM-56, SCRUM-58, SCRUM-106, SCRUM-107, SCRUM-108
A13: 2026-09-22 | B13: 0.3 | C13: Week 3 automated verification | D13: M | E13: Recorded the passed FE-01 auth/migration smoke gate, separate MinIO infrastructure healthcheck, and FE-04 execution/checklist acceptance evidence; recalculated Round 1 statistics without changing template case IDs or layout. | F13: `WorkflowBaselineTest`, `InspectionWorkflowTest`, `InspectionFixtureTest`, mobile inspection test, backend `mvnw verify`
A14: 2026-09-22 | B14: 0.4 | C14: FE-01 scope correction | D14: M | E14: Removed MinIO from the FE-01 foundation scope and linked evidence storage/MinIO to FE-04/WF3 task T025; retained the separate infrastructure healthcheck evidence. | F14: Jira SCRUM-58, SCRUM-85, SCRUM-108; Report 3 SRS 3.2 and 3.5
A15: 2026-09-22 | B15: 0.5 | C15: Workbook feature-sheet mapping clarification | D15: M | E15: Clarified that Feature 1/Feature 2 are fixed workbook sheets, while FE codes identify SRS capabilities and WF IDs identify business-flow test cases; documented the WF4-to-FE-07 mapping in Feature 2. | F15: `README.md`, `template-layout.md`, `test-case-list.md`, feature sources, and test statistics
A16: 2026-09-22 | B16: 0.6 | C16: FE-04/FE-05 case-boundary correction | D16: M | E16: Removed finding creation from the FE-04 evidence case and assigned AI candidate verification/manual findings to FE-05, preserving the existing WF3 test IDs. | F16: Report 3 SRS 3.5–3.6; FE-04 and FE-05 sources; `test-case-list.md`
A17: 2026-09-24 | B17: 0.7 | C17: FE-01 role-aware frontend navigation | D17: M | E17: Recorded automated portal, screen-access, multi-role entry, legacy redirect, and denied-route verification against the existing SRS matrix; functional workbook case IDs and statistics are unchanged. | F17: SmartDroneInspection-Frontend: `src/app/permissions/accessPolicy.test.ts`; Report 3 SRS 3.1.3
A18: 2026-09-24 | B18: 0.8 | C18: FE-01 browser authentication flow | D18: M | E18: Recorded frontend auth-contract, validation, session-return, and role-routing tests; implemented shared light login and Client registration without changing functional workbook case IDs or statistics. | F18: SmartDroneInspection-Frontend: `src/features/auth/`; Report 3 SRS 3.2; `npm.cmd test`
A19: 2026-09-24 | B19: 0.9 | C19: Shared API response contract | D19: M | E19: Recorded automated verification for the successful JSON envelope and unchanged Problem Details, 204, and binary-stream contracts; functional workbook case IDs and totals remain unchanged. | F19: Backend `ApiResponseTest` and API integration tests; frontend/mobile envelope tests; Report 3 sections 4.1 and 5.2
A20: 2026-09-24 | B20: 1.0 | C20: WF3 FE-04/FE-05/FE-06 automated verification | D20: M | E20: Recorded passing checklist/evidence, AI candidate/manual finding, and report totals and coverage while preserving all workbook sheets and stable WFx IDs. | F20: Jira SCRUM-85–SCRUM-93; backend `mvnw verify`; frontend and mobile regression; FE-04, FE-05, and FE-06 sources
A21: 2026-09-25 | B21: 1.1 | C21: WF3 S3 integration-test runner update | D21: M | E21: Recorded the unavailable MinIO CI image and successful S3Mock S3 API integration rerun; clarified that the CI mock does not replace MinIO runtime verification. | F21: Backend PR #44 CI runs 36090635549 and 36092639825; `EvidenceApiIntegrationTest`; `MinioEvidenceObjectStoreIntegrationTest`
... A45: 2026-10-10 | B45: 3.5 | C45: Workbook cell-level re-audit | D45: M | E45: Re-read the supplied workbook cell by cell, including borders, fills and column widths, and corrected three claims the first pass got wrong. (1) `Module code` was documented as carrying the sheet name; it is a formula reading the feature sheet's `Feature` cell `B2`, so it must carry the module name — corrected and cross-referenced to the `Feature 2` summary block. (2) The trailing columns `P:R` were described as inside a bordered summary block; they carry no border, `R2:R5` is a status legend and `Q10` is a borderless leftover fill. (3) The export metadata table listed `Cover` ranges that do not exist; `Version` has no merge, so its value belongs in `F6`, and exact label/value cells for all three sheets are now listed. Added the `Feature 1` summary block to `fe-03-…md` because `Test Statistics!C11` reads `Feature 1!B2` even though that sheet has no cases. **No case ID, status, round, date, tester, evidence or total changed** and no test execution is claimed; the supplied workbook was not edited. | F45: openpyxl read of values, formulas, merged ranges, borders and column widths across all five sheets; `template-layout.md`; `README.md`; `02-test-statistics/test-statistics.md`; `03-features/fe-03-…`, `fe-04-…`

Sheet Test Cases
D1: TEST CASE LIST
B3: Project Name | D3: SmartDroneInspection
B4: Project Code | D4: SEP490 — *confirm with project owner*
B5: Test Environment Setup Description | D5: <List enviroment requires in this system 1. Server 2. Database 3. Web Browser ... >
B8: No | C8: Function Name | D8: Sheet Name | E8: Description | F8: Pre-Condition
B9: 1 | C9: `[WF3-002]` FE-04 — MF3 evidence and traceability | D9: Feature 2 | E9: Assigned Inspector uploads supported evidence with a server-computed checksum and source metadata, retry-safe persistence, and scoped read access; the Inspector records the substantive evidence-quality decision. | F9: Assigned inspection past field work; valid image, PostgreSQL, and an S3-compatible endpoint (S3Mock in CI, MinIO at runtime).
B10: 2 | C10: `[WF3-003]` FE-05 — MF3 AI candidate and finding review | D10: Feature 2 | E10: Inspector reviews AI candidates or records a manual finding; pending/rejected detections stay non-official, and AI failure preserves the manual path. | F10: Accepted evidence set; deterministic inference stub or manual fallback available.
B11: 3 | C11: `[WF3-005]` FE-06 — MF3 human verification gates | D11: Feature 2 | E11: Candidates and the report draft are verified by the author Inspector and approved by a qualified ORG_ADMIN before publication; a manual structured draft remains possible when drafting is unavailable. | F11: Confirmed evidence set, an assigned Inspector, and a qualified reviewer in the same organization.
B12: 4 | C12: `[WF3-006]` FE-06 — MF3 immutable approved report | D12: Feature 2 | E12: The approved report version is immutable and source-traceable, and hands only repair-required findings to MF4. | F12: Published MF3 review artifacts exist.
B13: 5 | C13: `[WF3-009]` FE-04 — MF3 scoped inspection and report collections | D13: Feature 2 | E13: A caller reaches MF3 through a server-paged, role-scoped list instead of a hand-entered identifier; the report review queue is the same collection filtered to inspections that carry a report. | F13: Two organizations and fixtures for each of the four roles exist.

Sheet Test Statistics
B1: TEST STATISTICS
B3: Project Name | C3: <Project Name> | E3: Creator
B4: Project Code | C4: <Project Code> | E4: Reviewer/Approver
B5: Document Code | C5: =C4&"_"&"Test Report"&"_"&"vx.x" | E5: Issue Date | H5: <Date when this test report is created>
B6: Notes | C6: <List modules included in this release> ex: Release 1 includes 2 modules: Module1 and Module2
B10: No | C10: Module code | D10: Passed | E10: Failed | F10: Pending | G10: N/A | H10: Number of test cases
B11: 1 | C11: ='Feature 1'!B2 | D11: ='Feature 1'!B6 | E11: ='Feature 1'!C6 | F11: ='Feature 1'!D6 | G11: ='Feature 1'!E6 | H11: ='Feature 1'!B4
B12: 2 | C12: ='Feature 2'!B2 | D12: ='Feature 2'!B6 | E12: ='Feature 2'!C6 | F12: ='Feature 2'!D6 | G12: ='Feature 2'!E6 | H12: ='Feature 2'!B4
C14: Sub total | D14: =SUM(D9:D13) | E14: =SUM(E9:E13) | F14: =SUM(F9:F13) | G14: =SUM(G9:G13) | H14: =SUM(H9:H13)
C16: Test coverage | E16: =(D14+E14)*100/(H14-G14) | F16: %
C17: Test successful coverage | E17: =D14*100/(H14-G14) | F17: %

Sheet Feature 1
A2: Feature | R2: Passed
A3: Test requirement | R3: Failed
A4: Number of TCs | B4: =COUNTA(A12:A1000) | R4: Pending
A5: Testing Round | B5: Passed | C5: Failed | D5: Pending | E5: N/A | R5: N/A
A6: Round 1 | B6: =COUNTIF($F10:$F998,B5) | C6: =COUNTIF($F10:$F998,C5) | D6: =COUNTIF($F10:$F998,D5) | E6: =COUNTIF($F10:$F998,E5)
A7: Round 2 | B7: =COUNTIF($F10:$F998,B5) | C7: =COUNTIF($F10:$F998,C5) | D7: =COUNTIF($F10:$F998,D5) | E7: =COUNTIF($F10:$F998,E5)
A8: Round 3 | B8: =COUNTIF($F10:$F998,B5) | C8: =COUNTIF($F10:$F998,C5) | D8: =COUNTIF($F10:$F998,D5) | E8: =COUNTIF($F10:$F998,E5)
A10: Test Case ID | B10: Test Case Description | C10: Test Case Procedure | D10: Expected Results | E10: Pre-conditions | F10: Round 1 | G10: Test date | H10: Tester | I10: Round 2 | J10: Test date | K10: Tester | L10: Round 3 | M10: Test date | N10: Tester | O10: Note
A11: Function A

Sheet Feature 2
A2: Feature | R2: Passed
A3: Test requirement | R3: Failed
A4: Number of TCs | B4: =COUNTA(A12:A998) | R4: Pending
A5: Testing Round | B5: Passed | C5: Failed | D5: Pending | E5: N/A | R5: N/A
A6: Round 1 | B6: =COUNTIF($F10:$F996,B5) | C6: =COUNTIF($F10:$F996,C5) | D6: =COUNTIF($F10:$F996,D5) | E6: =COUNTIF($F10:$F996,E5)
A7: Round 2 | B7: =COUNTIF($F10:$F996,B5) | C7: =COUNTIF($F10:$F996,C5) | D7: =COUNTIF($F10:$F996,D5) | E7: =COUNTIF($F10:$F996,E5)
A8: Round 3 | B8: =COUNTIF($F10:$F996,B5) | C8: =COUNTIF($F10:$F996,C5) | D8: =COUNTIF($F10:$F996,D5) | E8: =COUNTIF($F10:$F996,E5)
A10: Test Case ID | B10: Test Case Description | C10: Test Case Procedure | D10: Expected Results | E10: Pre-conditions | F10: Round 1 | G10: Test date | H10: Tester | I10: Round 2 | J10: Test date | K10: Tester | L10: Round 3 | M10: Test date | N10: Tester | O10: Note
A11: Function D
A12: WF3-002 | B12: Assigned Inspector uploads supported evidence with checksum and source traceability and records the evidence-quality decision. | C12: Upload a valid PNG; retry the identical bytes; list and stream the evidence as the assignee and as a same-organization ORG_ADMIN; attempt upload and read as an unrelated Inspector; submit an unsupported content type and a half-supplied GPS pair; record an accepted decision with prose shot-list comparison; attempt a limited decision with no reason. | D12: Object-store bytes and PostgreSQL metadata remain consistent; checksum/source/uploader are server-traceable; an identical re-upload returns the existing evidence rather than a duplicate; out-of-scope Inspectors are refused; unsupported content and half-supplied GPS are rejected; a limited/return decision without a stated reason is refused; the Inspector's prose survives the round trip. | E12: An assigned inspection in `FIELD_COMPLETED` or `REPORT_DRAFT`, PostgreSQL, and an S3-compatible store (S3Mock in CI, MinIO at runtime) with a supported image available. | F12: Passed | I12: Pending | L12: Pending | O12: [FE-04] Verified by `InspectionEvidenceApiIntegrationTest` (10 tests), which ran again on 2026-10-09 within the full backend suite of 156 passing tests. Live MinIO runtime was exercised during the earlier browser walkthrough.
A13: WF3-009 | B13: A caller reaches MF3 through a server-paged, role-scoped list, and the report queue is the same collection filtered to inspections that carry a report. | C13: List as an assigned Inspector who also belongs to an organization holding an inspection assigned to someone else; list as a same-organization ORG_ADMIN; list as an ORG_ADMIN from another organization; list as a platform ADMIN; list as a MAINTENANCE_ENGINEER; request page 1 size 2 then page 3 of 5 rows; request `pageSize=5000`; filter to inspections with a report; read a row's inline report summary. | D13: An Inspector sees only assigned inspections and never a colleague's; an ORG_ADMIN sees their own organization only and another organization sees nothing; a platform ADMIN reads across organizations but has no write path; MAINTENANCE_ENGINEER is refused; paging reports `totalCount`/`totalPages` and the last page holds the remainder; an oversized page size is clamped to 100; `/with-reports` returns only inspections carrying a report and carries each row's `reportStatus`/`reportVersionNo`. | E13: Two organizations with fixtures for `INSPECTOR`, `ORG_ADMIN` and platform `ADMIN`, plus a `MAINTENANCE_ENGINEER`; PostgreSQL via Testcontainers. | F13: Passed | I13: Pending | L13: Pending | O13: [FE-04] Verified by `InspectionListApiIntegrationTest` (11 tests). The platform-ADMIN case asserts membership of both tenants rather than an absolute total, because the suite shares one container. Two test-helper defects were found and fixed during this run: creating a cross-tenant fixture inspection violated the composite `(asset_id, organization_id)` and `(inspector_id, organization_id)` foreign keys, which the helper had to satisfy.
A14: WF3-003 | B14: Inspector verifies AI candidates or records a manual finding. | C14: Request analysis before the Inspector accepts the evidence set; analyze a representative accepted image; verify its returned candidate provenance, confidence, normalized box, and pending status; attempt analysis as a different Inspector; record a manual finding with prose measurement; record the reviewer's decision on the finding. | D14: Analysis is refused until the Inspector accepts the evidence; valid model detections are persisted only as `PENDING`; out-of-scope Inspectors are refused; a manual finding is available without analysis; a finding is official only after a `CONFIRMED` or `MODIFIED` decision. | E14: An assigned `FIELD_COMPLETED` inspection, accepted image evidence, PostgreSQL, and an authorized Inspector and ORG_ADMIN in the same organization. | F14: Passed | I14: Pending | L14: Pending | O14: [FE-05] Verified with `InspectionReportApiIntegrationTest.analysisIsRefusedUntilTheInspectorAcceptsTheEvidence`, `analysisRequiresAssignmentAndAcceptedEvidenceAndPersistsOnlyPendingCandidates`, `manualFindingIsAvailableWithoutAnyAnalysis`, `aFindingMeasurementIsStorableAsProse`, and `anotherInspectorCannotAddAFinding`; plus `AiFindingCandidateTest` (4 candidate-review cases). These ran again on 2026-10-09 within the full backend suite of 156 passing tests. A live compatible-vision call against a Wikimedia Commons CC0 iron-bridge corrosion photograph returned three `PENDING` candidates with provider provenance and normalized boxes; the seeded 1x1 placeholder PNGs correctly returned none. No API key, prompt, or image bytes were recorded.
A15: WF3-005 | B15: AI Vision candidates and the inspection-report draft are verified by the author Inspector before ORG_ADMIN publication. | C15: Provide eligible confirmed evidence; attempt analysis before the Inspector accepts the evidence set; confirm analysis is refused and manual finding entry still works; author a draft (automated where configured, otherwise the manual structured draft); verify and submit as the author Inspector; attempt a return without a reason; return with a reason; attempt to review one's own report; resubmit and approve as a qualified ORG_ADMIN. | D15: Only human-confirmed findings enter official outputs; the author Inspector's authorship and the qualified ORG_ADMIN's independent approval are recorded; unverified draft text cannot be published; a failed or unconfigured drafting service still permits a structured manual draft under the same review gates. | E15: Assigned inspection with an accepted evidence quality decision and a qualified reviewer in the same organization. | F15: Passed | I15: Pending | L15: Pending | O15: [FE-06] Verified by `InspectionReportApiIntegrationTest`: `analysisIsRefusedUntilTheInspectorAcceptsTheEvidence`, `manualFindingIsAvailableWithoutAnyAnalysis`, `theAuthorCanWriteAStructuredDraftWhenAutomatedDraftingIsUnavailable`, `aManualDraftStillRefusesAnAuthorWithoutAnAcceptedEvidenceDecision`, `qualifiedReviewerCanReturnThenApproveThenPublish`, `reviewerCannotApproveTheAuthorsOwnReport`, and `listingVersionsOfAnInspectionWithoutAReportIsAnEmptyResult`; plus `InspectionReportVersionTest` (11 version-state cases). These ran again on 2026-10-09 within the full backend suite of 156 passing tests. The live external LLM-provider happy path remains unexecuted; the integration context configures no drafting provider, so the manual structured draft is the exercised path.
A16: WF3-006 | B16: MF3 publishes an immutable approved inspection report version and hands repair-required findings to MF4. | C16: Complete the MF3 review; publish the approved version; inspect the version metadata (author, reviewer, timestamps, evidence snapshot hash); confirm a published version is never edited; verify only repair-required findings are handed to MF4 and a no-repair outcome does not create an empty work order. | D16: The approved version is immutable and traceable; only repair-required findings become MF4 work orders; a no-repair outcome closes the inspection without inventing corrective scope. | E16: An approved MF3 report version and confirmed findings exist. | F16: Passed | I16: Pending | L16: Pending | O16: [FE-06] Verified by `InspectionReportApiIntegrationTest.publicationHandsOnlyConfirmedRepairRequiredFindingsToMaintenance`, which asserts `REPAIR_PENDING` plus that exactly one confirmed repair-required finding is handed to MF4, and by `listingVersionsOfAnInspectionWithoutAReportIsAnEmptyResult`. Re-run on 2026-10-09 within the full backend suite of 156 passing tests.
